moflask/__init__.py
moflask/flask.py
moflask/jwt.py
moflask/logging.py
moflask/pytest_plugin.py
moflask/sqlalchemy.py
moflask/wsgi.py
moflask/tests/__init__.py
moflask/tests/config_test.py
moflask/tests/flask_test.py
moflask/tests/jwt_test.py
moflask/tests/logging_test.py
moflask/tests/sqlalchemy_test.py
moflask/tests/wsgi_test.py
moflask/tests/test_app1/__init__.py
moflask/tests/test_app1/settings/__init__.py
moflask/tests/test_app1/settings/base.py
moflask/tests/test_app1/settings/independent.py
moflask/tests/test_app1/settings/overrides.py
moflask-2.2.1.dist-info/licenses/LICENSE.txt
moflask-2.2.1.dist-info/METADATA
moflask-2.2.1.dist-info/WHEEL
moflask-2.2.1.dist-info/entry_points.txt
moflask-2.2.1.dist-info/top_level.txt
moflask-2.2.1.dist-info/RECORD
